subprocess_executor/__init__.py
subprocess_executor/executor.py
subprocess_executor-1.0.1.dist-info/LICENCE.txt
subprocess_executor-1.0.1.dist-info/METADATA
subprocess_executor-1.0.1.dist-info/WHEEL
subprocess_executor-1.0.1.dist-info/top_level.txt
subprocess_executor-1.0.1.dist-info/RECORD
