Metadata-Version: 2.1
Name: subprocess-executor
Version: 1.0.1
Summary: Python Subprocess Executor Package
Home-page: https://github.com/dusanmitrovic98/python_subprocess_executor.git
Author: Dušan Mitrović
Author-email: dusanmitrovic@elfak.rs
Classifier: Intended Audience :: Developers
Classifier: License :: OSI Approved :: MIT License
Classifier: Programming Language :: Python
Classifier: Programming Language :: Python :: 3
Classifier: Operating System :: OS Independent
Classifier: Environment :: Console
Classifier: Topic :: System :: Shells
Classifier: Topic :: Utilities
License-File: LICENCE.txt
Requires-Dist: subprocess-executor
